ory_client_client/__init__.py
ory_client_client/api_client.py
ory_client_client/configuration.py
ory_client_client/exceptions.py
ory_client_client/model_utils.py
ory_client_client/rest.py
ory_client_client/api/__init__.py
ory_client_client/api/default_api.py
ory_client_client/apis/__init__.py
ory_client_client/model/__init__.py
ory_client_client/model/authenticate_ok_body.py
ory_client_client/model/container_change_response_item.py
ory_client_client/model/container_create_created_body.py
ory_client_client/model/container_top_ok_body.py
ory_client_client/model/container_update_ok_body.py
ory_client_client/model/container_wait_ok_body.py
ory_client_client/model/container_wait_ok_body_error.py
ory_client_client/model/create_identity.py
ory_client_client/model/create_recovery_link.py
ory_client_client/model/error_container.py
ory_client_client/model/error_response.py
ory_client_client/model/generic_error.py
ory_client_client/model/graph_driver_data.py
ory_client_client/model/health_not_ready_status.py
ory_client_client/model/health_status.py
ory_client_client/model/id_response.py
ory_client_client/model/identity.py
ory_client_client/model/identity_credentials.py
ory_client_client/model/image_delete_response_item.py
ory_client_client/model/image_summary.py
ory_client_client/model/inline_response200.py
ory_client_client/model/inline_response2001.py
ory_client_client/model/inline_response503.py
ory_client_client/model/json_error.py
ory_client_client/model/login_flow.py
ory_client_client/model/login_via_api_response.py
ory_client_client/model/meta.py
ory_client_client/model/plugin.py
ory_client_client/model/plugin_config.py
ory_client_client/model/plugin_config_args.py
ory_client_client/model/plugin_config_interface.py
ory_client_client/model/plugin_config_linux.py
ory_client_client/model/plugin_config_network.py
ory_client_client/model/plugin_config_rootfs.py
ory_client_client/model/plugin_config_user.py
ory_client_client/model/plugin_device.py
ory_client_client-0.0.1a1.dist-info/METADATA
ory_client_client-0.0.1a1.dist-info/WHEEL
ory_client_client-0.0.1a1.dist-info/top_level.txt
ory_client_client-0.0.1a1.dist-info/RECORD
