Metadata-Version: 2.1
Name: ory-client-client
Version: 0.0.1a1
Summary: Ory APIs
Home-page: https://github.com/ory/sdk
Author: API Support
Author-email: support@ory.sh
License: Apache 2.0
Keywords: OpenAPI,OpenAPI-Generator,Ory APIs
Platform: UNKNOWN
Requires-Python: >=3.6
Requires-Dist: urllib3 (>=1.25.3)
Requires-Dist: python-dateutil
